snakemake_argparse_bridge/__init__.py
snakemake_argparse_bridge/py.typed
snakemake_argparse_bridge-0.1.4.dist-info/METADATA
snakemake_argparse_bridge-0.1.4.dist-info/WHEEL
snakemake_argparse_bridge-0.1.4.dist-info/RECORD
