Metadata-Version: 2.4
Name: snakemake-argparse-bridge
Version: 0.1.4
Summary: Add your description here
Author-email: Cade Mirchandani <cmirchan@ucsc.edu>
Requires-Python: >=3.12
